pygenricher/GeneEnrichment.py
pygenricher/__init__.py
pygenricher/Data/all.gmt
pygenricher/Data/c2.cp.v7.4.symbols.gmt
pygenricher/Data/geneList_Fig5_qValue_cancerGenes.csv
pygenricher-0.0.27.dist-info/METADATA
pygenricher-0.0.27.dist-info/WHEEL
pygenricher-0.0.27.dist-info/entry_points.txt
pygenricher-0.0.27.dist-info/top_level.txt
pygenricher-0.0.27.dist-info/RECORD
